patgroom/__init__.py
patgroom/bar.py
patgroom/dispatcher.py
patgroom/dispatchprio.py
patgroom/eventprofiler.py
patgroom/logger.py
patgroom/marketsession.py
patgroom/observer.py
patgroom/plotter.py
patgroom/resamplebase.py
patgroom/warninghelpers.py
patgroom/barfeed/__init__.py
patgroom/barfeed/common.py
patgroom/barfeed/csvfeed.py
patgroom/barfeed/dbfeed.py
patgroom/barfeed/googlefeed.py
patgroom/barfeed/membf.py
patgroom/barfeed/ninjatraderfeed.py
patgroom/barfeed/quandlfeed.py
patgroom/barfeed/resampled.py
patgroom/barfeed/sqlitefeed.py
patgroom/barfeed/yahoofeed.py
patgroom/bitcoincharts/__init__.py
patgroom/bitcoincharts/barfeed.py
patgroom/bitstamp/__init__.py
patgroom/bitstamp/barfeed.py
patgroom/bitstamp/broker.py
patgroom/bitstamp/common.py
patgroom/bitstamp/httpclient.py
patgroom/bitstamp/livebroker.py
patgroom/bitstamp/livefeed.py
patgroom/bitstamp/wsclient.py
patgroom/broker/__init__.py
patgroom/broker/backtesting.py
patgroom/broker/fillstrategy.py
patgroom/broker/slippage.py
patgroom/database/__init__.py
patgroom/database/mysql_pool.py
patgroom/dataseries/__init__.py
patgroom/dataseries/aligned.py
patgroom/dataseries/bards.py
patgroom/dataseries/resampled.py
patgroom/exchange_api/__init__.py
patgroom/exchange_api/bitfinex1API.py
patgroom/exchange_api/bitfinex2API.py
patgroom/exchange_api/ss.py
patgroom/exchange_data/__init__.py
patgroom/exchange_data/bfx_data.py
patgroom/exchange_data/exchange_to_mysql.py
patgroom/feed/__init__.py
patgroom/feed/csvfeed.py
patgroom/feed/memfeed.py
patgroom/optimizer/__init__.py
patgroom/optimizer/base.py
patgroom/optimizer/local.py
patgroom/optimizer/serialization.py
patgroom/optimizer/server.py
patgroom/optimizer/worker.py
patgroom/optimizer/xmlrpcserver.py
patgroom/singal/__init__.py
patgroom/singal/position.py
patgroom/stratanalyzer/__init__.py
patgroom/stratanalyzer/drawdown.py
patgroom/stratanalyzer/returns.py
patgroom/stratanalyzer/sharpe.py
patgroom-1.1.0.dist-info/METADATA
patgroom-1.1.0.dist-info/RECORD
patgroom-1.1.0.dist-info/WHEEL
patgroom-1.1.0.dist-info/top_level.txt
