Metadata-Version: 2.1
Name: patgroom
Version: 1.1.0
Summary: pyalgotrade for python3
Home-page: https://github.com/groom-zhang/patgroom
Author: Groom
Author-email: earthworm6@163.com
License: MIT Licence
Keywords: pip,groom,pyalgotrade,groom,python3
Platform: any
Requires-Dist: numpy
